[
  { "CODCOLIGADA": 2, "CODFILIAL": 3, "CODOFERTA": "EM-MAT", "CODTURMA": "MAT-A", "HORARIO": "07:00-08:40", "CAPACIDADE": 35, "VAGAS": 12 },
  { "CODCOLIGADA": 2, "CODFILIAL": 3, "CODOFERTA": "EM-MAT", "CODTURMA": "MAT-B", "HORARIO": "13:00-14:40", "CAPACIDADE": 35, "VAGAS": 8 },
  { "CODCOLIGADA": 2, "CODFILIAL": 3, "CODOFERTA": "EM-POR", "CODTURMA": "POR-A", "HORARIO": "08:50-10:30", "CAPACIDADE": 35, "VAGAS": 15 },
  { "CODCOLIGADA": 2, "CODFILIAL": 3, "CODOFERTA": "EM-POR", "CODTURMA": "POR-B", "HORARIO": "14:50-16:30", "CAPACIDADE": 35, "VAGAS": 20 },
  { "CODCOLIGADA": 2, "CODFILIAL": 3, "CODOFERTA": "EM-HIS", "CODTURMA": "HIS-A", "HORARIO": "10:40-12:20", "CAPACIDADE": 35, "VAGAS": 5 },
  { "CODCOLIGADA": 2, "CODFILIAL": 3, "CODOFERTA": "EM-ART", "CODTURMA": "ART-A", "HORARIO": "07:00-08:40", "CAPACIDADE": 25, "VAGAS": 18 },
  { "CODCOLIGADA": 2, "CODFILIAL": 3, "CODOFERTA": "EM-FIL", "CODTURMA": "FIL-A", "HORARIO": "13:00-14:40", "CAPACIDADE": 25, "VAGAS": 22 },

  { "CODCOLIGADA": 9, "CODFILIAL": 1, "CODOFERTA": "EM-MAT", "CODTURMA": "MAT-A", "HORARIO": "07:00-08:40", "CAPACIDADE": 30, "VAGAS": 6 },
  { "CODCOLIGADA": 9, "CODFILIAL": 1, "CODOFERTA": "EM-MAT", "CODTURMA": "MAT-B", "HORARIO": "13:00-14:40", "CAPACIDADE": 30, "VAGAS": 14 },
  { "CODCOLIGADA": 9, "CODFILIAL": 1, "CODOFERTA": "EM-POR", "CODTURMA": "POR-A", "HORARIO": "08:50-10:30", "CAPACIDADE": 30, "VAGAS": 10 },
  { "CODCOLIGADA": 9, "CODFILIAL": 1, "CODOFERTA": "EM-HIS", "CODTURMA": "HIS-A", "HORARIO": "10:40-12:20", "CAPACIDADE": 30, "VAGAS": 18 },
  { "CODCOLIGADA": 9, "CODFILIAL": 1, "CODOFERTA": "EM-ART", "CODTURMA": "ART-A", "HORARIO": "07:00-08:40", "CAPACIDADE": 20, "VAGAS": 15 },
  { "CODCOLIGADA": 9, "CODFILIAL": 1, "CODOFERTA": "EM-FIL", "CODTURMA": "FIL-A", "HORARIO": "13:00-14:40", "CAPACIDADE": 20, "VAGAS": 19 },

  { "CODCOLIGADA": 18, "CODFILIAL": 2, "CODOFERTA": "EF-MAT", "CODTURMA": "MAT-A", "HORARIO": "07:00-08:40", "CAPACIDADE": 32, "VAGAS": 9 },
  { "CODCOLIGADA": 18, "CODFILIAL": 2, "CODOFERTA": "EF-MAT", "CODTURMA": "MAT-B", "HORARIO": "13:00-14:40", "CAPACIDADE": 32, "VAGAS": 17 },
  { "CODCOLIGADA": 18, "CODFILIAL": 2, "CODOFERTA": "EF-POR", "CODTURMA": "POR-A", "HORARIO": "08:50-10:30", "CAPACIDADE": 32, "VAGAS": 11 },
  { "CODCOLIGADA": 18, "CODFILIAL": 2, "CODOFERTA": "EF-CIE", "CODTURMA": "CIE-A", "HORARIO": "10:40-12:20", "CAPACIDADE": 28, "VAGAS": 7 },
  { "CODCOLIGADA": 18, "CODFILIAL": 2, "CODOFERTA": "EF-ART", "CODTURMA": "ART-A", "HORARIO": "07:00-08:40", "CAPACIDADE": 22, "VAGAS": 16 },
  { "CODCOLIGADA": 18, "CODFILIAL": 2, "CODOFERTA": "EF-EDF", "CODTURMA": "EDF-A", "HORARIO": "14:50-16:30", "CAPACIDADE": 40, "VAGAS": 25 },

  { "CODCOLIGADA": 8, "CODFILIAL": 1, "CODOFERTA": "EM-MAT", "CODTURMA": "MAT-A", "HORARIO": "07:00-08:40", "CAPACIDADE": 35, "VAGAS": 4 },
  { "CODCOLIGADA": 8, "CODFILIAL": 1, "CODOFERTA": "EM-MAT", "CODTURMA": "MAT-B", "HORARIO": "13:00-14:40", "CAPACIDADE": 35, "VAGAS": 13 },
  { "CODCOLIGADA": 8, "CODFILIAL": 1, "CODOFERTA": "EM-POR", "CODTURMA": "POR-A", "HORARIO": "08:50-10:30", "CAPACIDADE": 35, "VAGAS": 8 },
  { "CODCOLIGADA": 8, "CODFILIAL": 1, "CODOFERTA": "EM-HIS", "CODTURMA": "HIS-A", "HORARIO": "10:40-12:20", "CAPACIDADE": 35, "VAGAS": 21 },
  { "CODCOLIGADA": 8, "CODFILIAL": 1, "CODOFERTA": "EM-ART", "CODTURMA": "ART-A", "HORARIO": "07:00-08:40", "CAPACIDADE": 25, "VAGAS": 12 },
  { "CODCOLIGADA": 8, "CODFILIAL": 1, "CODOFERTA": "EM-FIL", "CODTURMA": "FIL-A", "HORARIO": "13:00-14:40", "CAPACIDADE": 25, "VAGAS": 20 }
]
